fs_nsfw_checker/__init__.py
fs_nsfw_checker/checker.py
fs_nsfw_checker-0.2.0.dist-info/METADATA
fs_nsfw_checker-0.2.0.dist-info/WHEEL
fs_nsfw_checker-0.2.0.dist-info/top_level.txt
fs_nsfw_checker-0.2.0.dist-info/RECORD
