Metadata-Version: 2.1
Name: fs_nsfw_checker
Version: 0.2.0
Summary: A package to check NSFW content in virtual try-on using the free FitSnap API
Home-page: https://github.com/parksoftware/fs-nsfw-checker
Author: FitSnap
Author-email: noreply@fitsnap.io
Classifier: Programming Language :: Python :: 3
Classifier: License :: OSI Approved :: MIT License
Classifier: Operating System :: OS Independent
Requires-Python: >=3.6
Requires-Dist: Pillow
Requires-Dist: requests
